{
  "source": "data/build_guides/ironclad/guide.md",
  "character": "Ironclad",
  "generated_at": "2026-04-09T17:18:35Z",
  "note": "Generated by scripts/build_guide_archetypes.py from guide.md.",
  "archetypes": {
    "strength": {
      "title": [
        "Strength Build"
      ],
      "signals": [
        "Twin Strike",
        "Fight Me!",
        "Inflame",
        "Demon Form"
      ],
      "early": [
        "Twin Strike"
      ],
      "mid": [
        "Fight Me!",
        "Inflame",
        "Rupture",
        "Whirlwind"
      ],
      "high": [
        "Demon Form",
        "Brand",
        "Thrash"
      ],
      "relics": [
        "Anchor",
        "Horn Cleat",
        "Permafrost",
        "Brimstone",
        "Ruined Helmet",
        "Sword of Jade"
      ]
    },
    "block": {
      "title": [
        "Block Build"
      ],
      "signals": [
        "Body Slam",
        "Shrug It Off",
        "Flame Barrier",
        "Taunt",
        "Juggernaut"
      ],
      "early": [
        "Body Slam",
        "Shrug It Off",
        "True Grit"
      ],
      "mid": [
        "Flame Barrier",
        "Taunt",
        "Stone Armor"
      ],
      "high": [
        "Juggernaut",
        "Barricade",
        "Crimson Mantle",
        "Impervious"
      ],
      "relics": [
        "Cloak Clasp",
        "Fresnel Lens",
        "Vambrace",
        "Sai",
        "Parrying Shield",
        "Pael's Legion",
        "Bronze Scales"
      ]
    },
    "exhaust": {
      "title": [
        "Exhaust Build"
      ],
      "signals": [
        "Corruption",
        "True Grit",
        "Ashen Strike",
        "Burning Pact",
        "Dark Embrace"
      ],
      "early": [
        "Corruption",
        "True Grit",
        "Body Slam"
      ],
      "mid": [
        "Ashen Strike",
        "Burning Pact",
        "Evil Eye",
        "Feel No Pain",
        "Forgotten Ritual"
      ],
      "high": [
        "Dark Embrace",
        "Brand",
        "Offering",
        "Pact's End",
        "Thrash",
        "Juggernaut"
      ],
      "relics": [
        "Charon's Ashes",
        "Forgotten Soul",
        "Burning Sticks",
        "Joss Paper"
      ]
    },
    "bloodletting": {
      "title": [
        "Bloodletting Build"
      ],
      "signals": [
        "Breakthrough",
        "Bloodletting",
        "Rupture",
        "Inferno",
        "Crimson Mantle"
      ],
      "early": [
        "Breakthrough",
        "Bloodletting"
      ],
      "mid": [
        "Rupture",
        "Inferno",
        "Hemokinesis"
      ],
      "high": [
        "Crimson Mantle",
        "Brand",
        "Offering",
        "Feed",
        "Tear Asunder"
      ],
      "relics": [
        "Centennial Puzzle",
        "Demon Tongue",
        "Self-Forming Clay"
      ]
    },
    "strike": {
      "title": [
        "Strike Build (Perfected Strike)"
      ],
      "signals": [
        "Perfected Strike",
        "Twin Strike",
        "Taunt",
        "Expect a Fight",
        "Pyre"
      ],
      "early": [
        "Perfected Strike",
        "Twin Strike",
        "Pommel Strike",
        "Breakthrough",
        "Tremble"
      ],
      "mid": [
        "Taunt",
        "Expect a Fight"
      ],
      "high": [
        "Pyre",
        "Hellraiser",
        "Colossus",
        "Cruelty"
      ],
      "relics": [
        "Strike Dummy",
        "Intimidating Helmet",
        "Any Ancient Energy relic"
      ]
    }
  }
}
